arkhon_memory/__init__.py
arkhon_memory/decay.py
arkhon_memory/lifecycle.py
arkhon_memory/memory_hub.py
arkhon_memory/schemas.py
arkhon_memory-0.1.0.dist-info/licenses/LICENSE
arkhon_memory-0.1.0.dist-info/METADATA
arkhon_memory-0.1.0.dist-info/WHEEL
arkhon_memory-0.1.0.dist-info/top_level.txt
arkhon_memory-0.1.0.dist-info/RECORD
