Metadata-Version: 2.4
Name: arkhon-memory
Version: 0.1.0
Summary: Lightweight, structured long-term memory layer for autonomous LLM agents.
Author-email: kissg96 <kissg@me.com>
License-Expression: MIT
Requires-Python: >=3.8
License-File: LICENSE
Requires-Dist: pydantic>=2.0.0
Dynamic: license-file
